MANIFEST.in
setup.py
django4facebook.egg-info/PKG-INFO
django4facebook.egg-info/SOURCES.txt
django4facebook.egg-info/dependency_links.txt
django4facebook.egg-info/not-zip-safe
django4facebook.egg-info/requires.txt
django4facebook.egg-info/top_level.txt
django_facebook/__init__.py
django_facebook/auth.py
django_facebook/decorators.py
django_facebook/middleware.py
django_facebook/templates/facebook_debug.html
django_facebook/templates/tags/facebook_init.html
django_facebook/templates/tags/facebook_load.html
django_facebook/templatetags/__init__.py
django_facebook/templatetags/facebook.py