Metadata-Version: 1.0
Name: django4facebook
Version: 0.1.0
Summary: Replace Django Authentication with Facebook
Home-page: http://github.com/pythonforfacebook/django-facebook
Author: Martey Dodoo
Author-email: django4facebook@marteydodoo.com
License: UNKNOWN
Platform: UNKNOWN
Classifier: Development Status :: 4 - Beta
Classifier: Environment :: Web Environment
Classifier: Framework :: Django
Classifier: Intended Audience :: Developers
Classifier: License :: OSI Approved :: MIT License
Classifier: Operating System :: OS Independent
Classifier: Programming Language :: Python
Classifier: Topic :: Software Development :: Libraries :: Python Modules
